{
    "coord": {
        "lon": -82.383,
        "lat": 23.133
    },
    "weather": [
        {
            "id": 802,
            "main": "Clouds",
            "description": "scattered clouds",
            "icon": "03d"
        }
    ],
    "base": "stations",
    "main": {
        "temp": 303.39,
        "feels_like": 307.79,
        "temp_min": 303.39,
        "temp_max": 303.44,
        "pressure": 1019,
        "humidity": 66
    },
    "visibility": 9000,
    "wind": {
        "speed": 5.14,
        "deg": 70
    },
    "clouds": {
        "all": 40
    },
    "dt": 1667492196,
    "sys": {
        "type": 1,
        "id": 7236,
        "country": "CU",
        "sunrise": 1667475348,
        "sunset": 1667515819
    },
    "timezone": -14400,
    "id": 3553478,
    "name": "Havana",
    "cod": 200
}